httpx_aws_auth/__init__.py
httpx_aws_auth/py.typed
httpx_aws_auth-4.1.1.dist-info/WHEEL
httpx_aws_auth-4.1.1.dist-info/METADATA
httpx_aws_auth-4.1.1.dist-info/RECORD
