Metadata-Version: 2.3
Name: httpx-aws-auth
Version: 4.1.1
Summary: Provides AWS authentication classes to be used with httpx authentication parameter
Author: Jakub Jantosik
Author-email: Jakub Jantosik <jakub.jantosik@gmail.com>
Classifier: Programming Language :: Python
Classifier: Programming Language :: Python :: 3
Classifier: Programming Language :: Python :: 3 :: Only
Classifier: Programming Language :: Python :: 3.10
Classifier: Programming Language :: Python :: 3.11
Classifier: Programming Language :: Python :: 3.12
Classifier: Programming Language :: Python :: 3.13
Classifier: Programming Language :: Python :: 3.14
Classifier: Intended Audience :: Developers
Classifier: Intended Audience :: Information Technology
Classifier: Operating System :: OS Independent
Classifier: Topic :: Software Development :: Libraries :: Python Modules
Classifier: Topic :: Internet
Requires-Dist: httpx>=0.28.0
Requires-Python: >=3.10
